record_convertor/__init__.py
record_convertor/command_processor/__init__.py
record_convertor/command_processor/command_helper/__init__.py
record_convertor/command_processor/command_helper/argument_check.py
record_convertor/command_processor/command_helper/geo_json.py
record_convertor/dataclass_processor/__init__.py
record_convertor/field_convertors/__init__.py
record_convertor/field_convertors/date_convertor.py
record_convertor/field_convertors/base_convertor/__init__.py
record_convertor/field_convertors/base_convertor/base_convertor.py
record_convertor/field_convertors/base_convertor/data_structure_conversions.py
record_convertor/field_convertors/base_convertor/generic_conversions.py
record_convertor/field_convertors/base_convertor/in_place_basic_conversions.py
record_convertor/field_convertors/base_convertor/key_values.py
record_convertor/field_convertors/base_convertor/base_convertor_helpers/__init__.py
record_convertor/field_convertors/base_convertor/base_convertor_helpers/countries.py
record_convertor/field_convertors/base_convertor/base_convertor_helpers/html_parser.py
record_convertor/field_convertors/base_convertor/base_convertor_helpers/string_helpers.py
record_convertor/field_convertors/base_convertor/base_convertor_helpers/data_files/__init__.py
record_convertor/field_convertors/base_convertor/base_convertor_helpers/data_files/country_codes.py
record_convertor/package_settings/__init__.py
record_convertor/package_settings/exceptions.py
record_convertor/package_settings/package_types.py
record_convertor/package_settings/protocol.py
record_convertor/package_settings/conditions/__init__.py
record_convertor/package_settings/conditions/evaluate.py
record_convertor/package_settings/conditions/condition_settings/__init__.py
record_convertor/package_settings/conditions/condition_settings/condition_types.py
record_convertor/package_settings/helpers/__init__.py
record_convertor/package_settings/helpers/dict_helper.py
record_convertor-1.1.6.dist-info/LICENSE
record_convertor-1.1.6.dist-info/METADATA
record_convertor-1.1.6.dist-info/WHEEL
record_convertor-1.1.6.dist-info/top_level.txt
record_convertor-1.1.6.dist-info/RECORD
